mosaic/__init__.py
mosaic/api/__init__.py
mosaic/api/accessors.py
mosaic/api/aggregators.py
mosaic/api/constructors.py
mosaic/api/enable.py
mosaic/api/functions.py
mosaic/api/fuse.py
mosaic/api/gdal.py
mosaic/api/predicates.py
mosaic/api/raster.py
mosaic/config/__init__.py
mosaic/config/config.py
mosaic/core/__init__.py
mosaic/core/library_handler.py
mosaic/core/mosaic_context.py
mosaic/lib/__init__.py
mosaic/lib/mosaic-0.4.3-jar-with-dependencies.jar
mosaic/lib/mosaic-0.4.3.jar
mosaic/models/__init__.py
mosaic/models/analyzer/__init__.py
mosaic/models/analyzer/analyzer.py
mosaic/models/knn/__init__.py
mosaic/models/knn/spatial_knn.py
mosaic/readers/__init__.py
mosaic/readers/mosaic_data_frame_reader.py
mosaic/readers/readers.py
mosaic/resources/__init__.py
mosaic/resources/mosaic_logo.png
mosaic/utils/__init__.py
mosaic/utils/display_handler.py
mosaic/utils/kepler_config.py
mosaic/utils/kepler_magic.py
mosaic/utils/notebook_utils.py
mosaic/utils/scala_utils.py
mosaic/utils/types.py
test/__init__.py
test/context.py
test/test_checkpoint.py
test/test_display_handler.py
test/test_fuse_install.py
test/test_gdal_install.py
test/test_library_handler.py
test/test_mosaic.py
test/test_raster_functions.py
test/test_vector_functions.py
test/utils/__init__.py
test/utils/mosaic_test_case.py
test/utils/mosaic_test_case_with_gdal.py
test/utils/setup_fuse.py
test/utils/setup_gdal.py
test/utils/spark_test_case.py
databricks_mosaic-0.4.3.dist-info/METADATA
databricks_mosaic-0.4.3.dist-info/WHEEL
databricks_mosaic-0.4.3.dist-info/top_level.txt
databricks_mosaic-0.4.3.dist-info/RECORD
